venvkit/__init__.py
venvkit/main.py
venvkit-0.2.1.dist-info/METADATA
venvkit-0.2.1.dist-info/WHEEL
venvkit-0.2.1.dist-info/entry_points.txt
venvkit-0.2.1.dist-info/top_level.txt
venvkit-0.2.1.dist-info/RECORD
