Metadata-Version: 2.1
Name: venvkit
Version: 0.2.1
Summary: A powerful toolkit for Python virtual environment management
Home-page: https://github.com/UmarBalak/venvkit
Author: Umar Balak
Project-URL: Documentation, https://github.com/UmarBalak/venvkit/blob/main/README.md
Project-URL: Source, https://github.com/UmarBalak/venvkit
Keywords: venv,virtualenv,environment,python,development,tools,cli
Classifier: Intended Audience :: Developers
Classifier: Programming Language :: Python :: 3
Classifier: Programming Language :: Python :: 3.8
Classifier: Programming Language :: Python :: 3.9
Classifier: Programming Language :: Python :: 3.10
Classifier: Programming Language :: Python :: 3.11
Classifier: Programming Language :: Python :: 3.12
Classifier: Topic :: Software Development
Classifier: Topic :: Software Development :: Build Tools
Classifier: Topic :: Software Development :: Libraries :: Python Modules
Classifier: Topic :: System :: Installation/Setup
Classifier: Topic :: System :: Systems Administration
Classifier: Topic :: Utilities
Classifier: Natural Language :: English
Requires-Python: >=3.8
